setup.py
demo/__init__.py
demo.egg-info/PKG-INFO
demo.egg-info/SOURCES.txt
demo.egg-info/dependency_links.txt
demo.egg-info/not-zip-safe
demo.egg-info/top_level.txt