Metadata-Version: 1.0
Name: demo
Version: 0.1.0
Summary: egg test demo.
Home-page: UNKNOWN
Author: amoblin
Author-email: amoblin@ossxp.com
License: GPL
Keywords: test,egg
Platform: Independant
